checkbox_api/__init__.py
checkbox_api/client/__init__.py
checkbox_api/client/async.py
checkbox_api/client/base.py
checkbox_api/client/sync.py
checkbox_api/consts.py
checkbox_api/exceptions.py
checkbox_api/methods/__init__.py
checkbox_api/methods/base.py
checkbox_api/methods/cash_register.py
checkbox_api/methods/cashier.py
checkbox_api/methods/organization.py
checkbox_api/methods/receipts.py
checkbox_api/methods/reports.py
checkbox_api/methods/shifts.py
checkbox_api/methods/tax.py
checkbox_api/methods/transactions.py
checkbox_api/methods/update_channel.py
checkbox_api/session.py
checkbox_api/storage/__init__.py
checkbox_api/storage/simple.py
checkbox_api-0.1.41.dist-info/METADATA
checkbox_api-0.1.41.dist-info/WHEEL
checkbox_api-0.1.41.dist-info/RECORD
