Metadata-Version: 2.1
Name: checkbox-api
Version: 0.1.41
Summary: checkbox.in.ua Transactional Processing API Client
License: MIT
Author: Oleksandr Onufriichuk
Author-email: oleksandr.onufriichuk@itvaan.com.ua
Requires-Python: >=3.8,<4.0
Classifier: License :: OSI Approved :: MIT License
Classifier: Programming Language :: Python :: 3
Classifier: Programming Language :: Python :: 3.8
Classifier: Programming Language :: Python :: 3.9
Classifier: Programming Language :: Python :: 3.10
Classifier: Programming Language :: Python :: 3.11
Requires-Dist: PyJWT (>=1.7.1,<2.0.0)
Requires-Dist: httpx (==0.13.3)
